cv2imageload/__init__.py
cv2imageload/imgload.py
cv2imageload/imgloadexception.py
tests/__init__.py
tests/test_loadimage_from_file.py
cv2imageload-1.0.6.dist-info/METADATA
cv2imageload-1.0.6.dist-info/WHEEL
cv2imageload-1.0.6.dist-info/top_level.txt
cv2imageload-1.0.6.dist-info/RECORD
