Metadata-Version: 2.1
Name: cv2imageload
Version: 1.0.6
Summary: python cv2 load image from image file, url or base64 code of image
Home-page: https://github.com/ShawnZhang31/cv2ImageLoad.git
Author: Shawn Zhang
Author-email: shawnzhang31@gmail.com
License: UNKNOWN
Platform: UNKNOWN
Classifier: Programming Language :: Python :: 3
Classifier: License :: OSI Approved :: MIT License
Classifier: Operating System :: OS Independent
Requires-Python: >=3.0
Requires-Dist: opencv-contrib-python
Requires-Dist: validators
